heisenbug/__init__.py
heisenbug/heisenbug.py
heisenbug-0.0.1.dist-info/LICENSE
heisenbug-0.0.1.dist-info/METADATA
heisenbug-0.0.1.dist-info/WHEEL
heisenbug-0.0.1.dist-info/top_level.txt
heisenbug-0.0.1.dist-info/RECORD
