Metadata-Version: 2.1
Name: heisenbug
Version: 0.0.1
Summary: Hello Quantum!
Home-page: https://github.com/heisenbugco/heisenbug
Author: heisenbug.co
Author-email: heisenbugco@gmail.com
License: UNKNOWN
Download-URL: https://github.com/heisenbugco/heisenbug/archive/v_001.tar.gz
Keywords: quantum,machine,learning
Platform: UNKNOWN
Classifier: Development Status :: 3 - Alpha
Classifier: Intended Audience :: Developers
Classifier: Intended Audience :: Education
Classifier: Intended Audience :: Science/Research
Classifier: Topic :: Scientific/Engineering :: Artificial Intelligence
Classifier: License :: OSI Approved :: Apache Software License
Classifier: Programming Language :: Python :: 3
Classifier: Programming Language :: Python :: 3.4
Classifier: Programming Language :: Python :: 3.5
Classifier: Programming Language :: Python :: 3.6
Classifier: Programming Language :: Python :: 3.7
Classifier: Programming Language :: Python :: 3.8
Classifier: Programming Language :: Python :: 3.9
